userena/__init__.py
userena/admin.py
userena/apps.py
userena/backends.py
userena/compat.py
userena/contrib/__init__.py
userena/contrib/umessages/__init__.py
userena/contrib/umessages/admin.py
userena/contrib/umessages/fields.py
userena/contrib/umessages/fixtures/messages.json
userena/contrib/umessages/forms.py
userena/contrib/umessages/managers.py
userena/contrib/umessages/migrations/0001_initial.py
userena/contrib/umessages/migrations/__init__.py
userena/contrib/umessages/models.py
userena/contrib/umessages/signals.py
userena/contrib/umessages/templates/base.html
userena/contrib/umessages/templates/umessages/base_message.html
userena/contrib/umessages/templates/umessages/message_detail.html
userena/contrib/umessages/templates/umessages/message_form.html
userena/contrib/umessages/templates/umessages/message_list.html
userena/contrib/umessages/templatetags/__init__.py
userena/contrib/umessages/templatetags/umessages_tags.py
userena/contrib/umessages/tests/__init__.py
userena/contrib/umessages/tests/test_fields.py
userena/contrib/umessages/tests/test_forms.py
userena/contrib/umessages/tests/test_managers.py
userena/contrib/umessages/tests/test_models.py
userena/contrib/umessages/tests/test_views.py
userena/contrib/umessages/urls.py
userena/contrib/umessages/views.py
userena/decorators.py
userena/fixtures/profiles.json
userena/fixtures/users.json
userena/forms.py
userena/locale/ar/LC_MESSAGES/django.mo
userena/locale/ar/LC_MESSAGES/django.po
userena/locale/bg/LC_MESSAGES/django.mo
userena/locale/bg/LC_MESSAGES/django.po
userena/locale/de/LC_MESSAGES/django.mo
userena/locale/de/LC_MESSAGES/django.po
userena/locale/de_du/LC_MESSAGES/django.mo
userena/locale/de_du/LC_MESSAGES/django.po
userena/locale/el/LC_MESSAGES/django.mo
userena/locale/el/LC_MESSAGES/django.po
userena/locale/es/LC_MESSAGES/django.mo
userena/locale/es/LC_MESSAGES/django.po
userena/locale/fr/LC_MESSAGES/django.mo
userena/locale/fr/LC_MESSAGES/django.po
userena/locale/gl/LC_MESSAGES/django.po
django_userena_ce-7.0.3.dist-info/LICENSE
django_userena_ce-7.0.3.dist-info/METADATA
django_userena_ce-7.0.3.dist-info/WHEEL
django_userena_ce-7.0.3.dist-info/RECORD
