Metadata-Version: 2.1
Name: django-userena-ce
Version: 7.0.3
Summary: Complete user management application for Django
Home-page: https://github.com/django-userena-ce/django-userena-ce
License: BSD-3-Clause
Author: James Meakin
Author-email: django-userena-ce@jmsmkn.com
Requires-Python: >=3.8,<4.0
Classifier: Development Status :: 5 - Production/Stable
Classifier: Environment :: Web Environment
Classifier: Framework :: Django
Classifier: Framework :: Django :: 3.2
Classifier: Framework :: Django :: 4.1
Classifier: Framework :: Django :: 4.2
Classifier: Intended Audience :: Developers
Classifier: License :: OSI Approved :: BSD License
Classifier: Operating System :: OS Independent
Classifier: Programming Language :: Python :: 3
Classifier: Programming Language :: Python :: 3.8
Classifier: Programming Language :: Python :: 3.9
Classifier: Programming Language :: Python :: 3.10
Classifier: Programming Language :: Python :: 3.11
Classifier: Topic :: Utilities
Requires-Dist: Django (>=3.2)
Requires-Dist: django-guardian (>=2.0)
Requires-Dist: easy-thumbnails
Requires-Dist: html2text
Project-URL: Repository, https://github.com/django-userena-ce/django-userena-ce
